nlp_basictasks/Trainer.py
nlp_basictasks/__init__.py
nlp_basictasks/log.py
nlp_basictasks/evaluation/__init__.py
nlp_basictasks/evaluation/attackEvaluator.py
nlp_basictasks/evaluation/clsEvaluator.py
nlp_basictasks/evaluation/nerEvaluator.py
nlp_basictasks/evaluation/pairclsEvaluator.py
nlp_basictasks/evaluation/stsEvaluator.py
nlp_basictasks/heads/__init__.py
nlp_basictasks/heads/attack_for_cls.py
nlp_basictasks/heads/base_head.py
nlp_basictasks/heads/cls.py
nlp_basictasks/heads/cluster.py
nlp_basictasks/heads/mrc.py
nlp_basictasks/heads/ner.py
nlp_basictasks/heads/sts.py
nlp_basictasks/heads/utils.py
nlp_basictasks/modules/BERT.py
nlp_basictasks/modules/LSTM.py
nlp_basictasks/modules/MLP.py
nlp_basictasks/modules/Pooling.py
nlp_basictasks/modules/SBERT.py
nlp_basictasks/modules/__init__.py
nlp_basictasks/modules/utils.py
nlp_basictasks/modules/transformers/__init__.py
nlp_basictasks/modules/transformers/configuration_bert.py
nlp_basictasks/modules/transformers/log.py
nlp_basictasks/modules/transformers/modeling_bert.py
nlp_basictasks/modules/transformers/optimization.py
nlp_basictasks/modules/transformers/tokenization_bert.py
nlp_basictasks/readers/__init__.py
nlp_basictasks/readers/base_reader.py
nlp_basictasks/readers/cls.py
nlp_basictasks/readers/cluster.py
nlp_basictasks/readers/mrc.py
nlp_basictasks/readers/ner.py
nlp_basictasks/readers/paircls.py
nlp_basictasks/readers/sts.py
nlp_basictasks/tasks/__init__.py
nlp_basictasks/tasks/cls.py
nlp_basictasks/tasks/mrc.py
nlp_basictasks/tasks/ner.py
nlp_basictasks/tasks/sts.py
nlp_basictasks/tasks/utils.py
nlp_basictasks/webservices/__init__.py
nlp_basictasks/webservices/log.py
nlp_basictasks/webservices/sts_retrieve.py
nlp_basictasks-0.2.2.dist-info/LICENSE
nlp_basictasks-0.2.2.dist-info/METADATA
nlp_basictasks-0.2.2.dist-info/WHEEL
nlp_basictasks-0.2.2.dist-info/top_level.txt
nlp_basictasks-0.2.2.dist-info/RECORD
